sambanova/__init__.py
sambanova/api_client.py
sambanova/utils.py
sambanova/audio/__init__.py
sambanova/audio/audio.py
sambanova/chat/__init__.py
sambanova/chat/chat_completion.py
sambanova/embeddings/__init__.py
sambanova/embeddings/embeddings.py
sambanova/image/__init__.py
sambanova/image/image.py
sambanova/model_list/__init__.py
sambanova/model_list/models.py
sambanova/transcription/__init__.py
sambanova/transcription/transcription.py
sambanova/translation/__init__.py
sambanova/translation/translation.py
sambanova_pysdk-1.0.3.dist-info/METADATA
sambanova_pysdk-1.0.3.dist-info/WHEEL
sambanova_pysdk-1.0.3.dist-info/top_level.txt
sambanova_pysdk-1.0.3.dist-info/RECORD
