Metadata-Version: 2.4
Name: sambanova-pysdk
Version: 1.0.3
Summary: A Python SDK for the SambaNova cloud API
Author-email: Santhoshreddyva <santhoshreddyva@gmail.com>
Project-URL: Homepage, https://github.com/Santhoshreddyva/sambanova-sdk
Requires-Dist: requests>=2.31.0
